sharenotelib/__about__.py
sharenotelib/__init__.py
sharenotelib/snip00.py
sharenotelib-0.1.3.dist-info/METADATA
sharenotelib-0.1.3.dist-info/WHEEL
sharenotelib-0.1.3.dist-info/licenses/LICENSE
sharenotelib-0.1.3.dist-info/RECORD
