Metadata-Version: 2.4
Name: sharenotelib
Version: 0.1.3
Summary: Reference Python SDK for Sharenote clients
Project-URL: Homepage, https://github.com/soprinter/sharenotelib
Project-URL: Repository, https://github.com/soprinter/sharenotelib
Author: Soprinter
License: CC0-1.0
License-File: LICENSE
Keywords: nostr,proof-of-work,sdk,sharenote
Classifier: Intended Audience :: Developers
Classifier: License :: CC0 1.0 Universal (CC0 1.0) Public Domain Dedication
Classifier: Programming Language :: Python :: 3
Classifier: Programming Language :: Python :: 3 :: Only
Classifier: Topic :: Software Development :: Libraries
Requires-Python: >=3.9
